kmi2122-0.1.10.data/data/kmi2122_dataset/dataset.json
kmi2122_dataset/__init__.py
kmi2122_dataset/dataset.json
kmi2122_dataset/unit_test.py
kmi2122-0.1.10.dist-info/LICENSE
kmi2122-0.1.10.dist-info/METADATA
kmi2122-0.1.10.dist-info/WHEEL
kmi2122-0.1.10.dist-info/top_level.txt
kmi2122-0.1.10.dist-info/RECORD
