Metadata-Version: 2.1
Name: kmi2122
Version: 0.1.10
Summary: This dataset includes some macroeconomic indicators for South Korea in 2021-2022.
Home-page: https://github.com/DSDanielPark/kmi2122-dataset
Author: parkminwoo
Author-email: parkminwoo1991@gmail.com
Requires-Python: >=3.6
License-File: LICENSE
Requires-Dist: jsons
Requires-Dist: pandas
